LICENSE
MANIFEST.in
README.rst
setup.py
cbv/__init__.py
cbv/http.py
cbv/middleware.py
cbv/views/__init__.py
cbv/views/base.py
cbv/views/create_update.py
cbv/views/date_based.py
cbv/views/dates.py
cbv/views/detail.py
cbv/views/edit.py
cbv/views/list.py
cbv/views/list_detail.py
cbv/views/simple.py
django_cbv.egg-info/PKG-INFO
django_cbv.egg-info/SOURCES.txt
django_cbv.egg-info/dependency_links.txt
django_cbv.egg-info/not-zip-safe
django_cbv.egg-info/top_level.txt