Metadata-Version: 1.0
Name: django-cbv
Version: 0.2
Summary: Django class-based views, backported from Django trunk
Home-page: https://github.com/brutasse/django-cbv
Author: Bruno Renie
Author-email: buburno@gmail.com
License: BSD
Platform: any
Classifier: Development Status :: 3 - Alpha
Classifier: Environment :: Web Environment
Classifier: Intended Audience :: Developers
Classifier: License :: OSI Approved :: BSD License
Classifier: Operating System :: OS Independent
Classifier: Programming Language :: Python
Classifier: Topic :: Internet :: WWW/HTTP :: Dynamic Content
Classifier: Framework :: Django
